cli/__init__.py
cli/main.py
django_cli_g73-0.2.0.dist-info/LICENSE
django_cli_g73-0.2.0.dist-info/METADATA
django_cli_g73-0.2.0.dist-info/WHEEL
django_cli_g73-0.2.0.dist-info/dependency_links.txt
django_cli_g73-0.2.0.dist-info/entry_points.txt
django_cli_g73-0.2.0.dist-info/top_level.txt
django_cli_g73-0.2.0.dist-info/RECORD
