Metadata-Version: 2.1
Name: django-cli-g73
Version: 0.2.0
Summary: This is a small project created with the initial purpose of facilitating, through a single command, the creation of views(views), templates(templates), models(models) and serializers(serializers) for the django web framework.
Home-page: https://github.com/wdavid73/django-cli
Author: Wilson Padilla
Author-email: wdavidw26@gmail.com
License: MIT
Platform: UNKNOWN
Classifier: Programming Language :: Python :: 2.7
Classifier: Programming Language :: Python :: 3
Classifier: Programming Language :: Python :: 3.7
Classifier: Programming Language :: Python :: 3.8
Classifier: License :: OSI Approved :: MIT License
Classifier: Operating System :: OS Independent
Requires-Python: >=3.6
Requires-Dist: blessings (==1.7)
Requires-Dist: click (==7.1.2)
Requires-Dist: curtsies (==0.3.4)
Requires-Dist: enquiries (==0.1.0)
Requires-Dist: pyfiglet (==0.8.post1)
Requires-Dist: six (==1.15.0)
Requires-Dist: wcwidth (==0.2.5)
